jade/__init__.py
jadelib-0.1.0.dist-info/METADATA
jadelib-0.1.0.dist-info/WHEEL
jadelib-0.1.0.dist-info/top_level.txt
jadelib-0.1.0.dist-info/RECORD
