Metadata-Version: 2.4
Name: jadelib
Version: 0.1.0
Summary: A JAX-based library for statistical machine learning.
Author-email: Michael Drolet <michael.drolet@tu-darmstadt.de>
License: MIT
Project-URL: Homepage, https://github.com/mdrolet01/jade.git
Project-URL: Repository, https://github.com/mdrolet01/jade.git
Requires-Python: >=3.10
Requires-Dist: jax
Requires-Dist: flax
